box/__init__.py
box/auth_success.html
box/box_auth.py
box/box_config.py
box/streamlit_box_ui.py
database/__init__.py
database/eyeon-ddl.sql
database/eyeon-dqa.sql
database/observations.json
eyeon/__init__.py
eyeon/checksum.py
eyeon/observe.py
eyeon/parse.py
eyeon/upload.py
eyeon/cli/__init__.py
peyeon-0.0.0rc6.dist-info/licenses/LICENSE
peyeon-0.0.0rc6.dist-info/licenses/NOTICE
streamlit/Dockerfile
streamlit/README.md
streamlit/eyeon_settings.toml
streamlit/main.py
streamlit/requirements.txt
streamlit/.streamlit/config.toml
streamlit/common/EyeON_logo.png
streamlit/common/__init__.py
streamlit/common/debug_page.py
streamlit/common/dqautil.py
streamlit/common/page_frags.py
streamlit/common/queries.sql
streamlit/common/rawutil.py
streamlit/common/st_content_util.py
streamlit/common/st_graph_util.py
streamlit/common/utils.py
streamlit/pages/__init__.py
streamlit/pages/_base_page.py
streamlit/pages/certs.py
streamlit/pages/debug_page.py
streamlit/pages/initial_page.py
streamlit/pages/metadata.py
streamlit/pages/pages.py
streamlit/utils/__init__.py
streamlit/utils/config.py
peyeon-0.0.0rc6.dist-info/METADATA
peyeon-0.0.0rc6.dist-info/WHEEL
peyeon-0.0.0rc6.dist-info/entry_points.txt
peyeon-0.0.0rc6.dist-info/top_level.txt
peyeon-0.0.0rc6.dist-info/RECORD
