Metadata-Version: 2.4
Name: peyeon
Version: 0.0.0rc6
Summary: EyeON update tracking utility
Author-email: Seth Lyles <lyles6@llnl.gov>, Wangmo Tenzing <tenzing1@llnl.gov>, Jack Mooney <mooney7@llnl.gov>, Grant Johnson <johnson30@llnl.gov>, Isabel Gardner <gardner59@llnl.gov>, Grant Espe <espe1@llnl.gov>
Maintainer-email: Seth Lyles <lyles6@llnl.gov>
License: MIT License
Requires-Python: >=3.9
License-File: LICENSE
License-File: NOTICE
Requires-Dist: jsonschema>=4.17
Requires-Dist: lief>=0.13.2
Requires-Dist: python-magic==0.4.27
Requires-Dist: pefile>=2024.8.26
Requires-Dist: telfhash>=0.9.8
Requires-Dist: surfactant[java,macho]==0.0.0rc15
Requires-Dist: coverage>=7.5.3
Requires-Dist: duckdb>=1.0.0
Requires-Dist: alive_progress>=3.1.5
Requires-Dist: dynaconf>=3.2.6
Requires-Dist: streamlit>=1.37.0
Requires-Dist: jupyter>=1.1.1
Requires-Dist: requests>=2.32.4
Requires-Dist: toml>=0.10.2
Requires-Dist: boxsdk==3.14.0
Requires-Dist: pydantic_settings>=2.10.1
Provides-Extra: dev
Requires-Dist: build; extra == "dev"
Requires-Dist: pre-commit; extra == "dev"
Requires-Dist: black; extra == "dev"
Provides-Extra: docs
Requires-Dist: sphinx; extra == "docs"
Dynamic: license-file
